impression_client/__init__.py
impression_client/admin.py
impression_client/apps.py
impression_client/backends.py
impression_client/models.py
impression_client/settings.py
impression_client/tests.py
impression_client/urls.py
impression_client/wsgi.py
impression_client/migrations/0001_initial.py
impression_client/migrations/__init__.py
django_impression_client-0.6.5.dist-info/LICENSE
django_impression_client-0.6.5.dist-info/METADATA
django_impression_client-0.6.5.dist-info/WHEEL
django_impression_client-0.6.5.dist-info/top_level.txt
django_impression_client-0.6.5.dist-info/RECORD
