Metadata-Version: 2.1
Name: django-impression-client
Version: 0.6.5
Summary: Client app for Impression.
Home-page: https://github.com/gregschmit/django-impression-client
Author: Gregory N. Schmit
Author-email: schmitgreg@gmail.com
License: MIT
Platform: UNKNOWN
Classifier: Environment :: Web Environment
Classifier: Framework :: Django
Classifier: Framework :: Django :: 2.0
Classifier: Framework :: Django :: 2.1
Classifier: Framework :: Django :: 2.2
Classifier: Framework :: Django :: 3.0
Classifier: Intended Audience :: Developers
Classifier: License :: OSI Approved :: MIT License
Classifier: Programming Language :: Python :: 3
Requires-Dist: Django (>=2)
Requires-Dist: requests (>=2)
